AUTHORS
COPYING
pyknp/__init__.py
pyknp/evaluate/__init__.py
pyknp/evaluate/dep.py
pyknp/evaluate/mrph.py
pyknp/evaluate/phrase.py
pyknp/evaluate/scorer.py
pyknp/juman/__init__.py
pyknp/juman/juman.py
pyknp/juman/mlist.py
pyknp/juman/morpheme.py
pyknp/knp/__init__.py
pyknp/knp/blist.py
pyknp/knp/bunsetsu.py
pyknp/knp/drawtree.py
pyknp/knp/features.py
pyknp/knp/knp.py
pyknp/knp/pas.py
pyknp/knp/rel.py
pyknp/knp/syngraph.py
pyknp/knp/tag.py
pyknp/knp/tlist.py
pyknp/scripts/knp_drawtree.py
pyknp/utils/__init__.py
pyknp/utils/analyzer.py
pyknp/utils/loader.py
pyknp/utils/process.py
pyknp-0.6.0.dist-info/entry_points.txt
pyknp-0.6.0.dist-info/COPYING
pyknp-0.6.0.dist-info/WHEEL
pyknp-0.6.0.dist-info/METADATA
pyknp-0.6.0.dist-info/RECORD
