Metadata-Version: 2.1
Name: pyknp
Version: 0.6.0
Summary: Python module for JUMAN/KNP
Home-page: https://github.com/ku-nlp/pyknp
License: See COPYING
Keywords: NLP,JUMAN,KNP
Author: Kurohashi-Kawahara Lab, Kyoto Univ
Author-email: contact@nlp.ist.i.kyoto-u.ac.jp
Maintainer: Nobuhiro Ueda
Maintainer-email: ueda@nlp.ist.i.kyoto-u.ac.jp
Requires-Python: >=3.7,<4.0
Classifier: License :: Other/Proprietary License
Classifier: Programming Language :: Python :: 2.7
Classifier: Programming Language :: Python :: 3
Classifier: Programming Language :: Python :: 3.6
Classifier: Programming Language :: Python :: 3.7
Classifier: Programming Language :: Python :: 3.8
Classifier: Programming Language :: Python :: 3.9
Requires-Dist: six
Project-URL: Documentation, https://pyknp.readthedocs.io/en/latest/
Project-URL: Repository, https://github.com/ku-nlp/pyknp
